README.rst
setup.py
number_types/__init__.py
number_types/coordinates.py
number_types/tests.py
number_types/typed_complex.py
number_types.egg-info/PKG-INFO
number_types.egg-info/SOURCES.txt
number_types.egg-info/dependency_links.txt
number_types.egg-info/top_level.txt