Metadata-Version: 1.1
Name: number-types
Version: 0.0.5
Summary: Various number types for Python
Home-page: https://github.com/MitalAshok/number_types
Author: Mital Ashok
Author-email: mital.vaja@googlemail.com
License: MIT
Keywords: types,number,coordinates,complex
Platform: any
Classifier: Development Status :: 3 - Alpha
Classifier: Intended Audience :: Developers
Classifier: License :: OSI Approved :: MIT License
Classifier: Operating System :: OS Independent
Classifier: Programming Language :: Python :: 2
Classifier: Programming Language :: Python :: 2.7
Classifier: Programming Language :: Python :: 3
Classifier: Programming Language :: Python :: 3.3
Classifier: Programming Language :: Python :: 3.4
Classifier: Programming Language :: Python :: 3.5
Classifier: Programming Language :: Python :: 3.6
Classifier: Topic :: Software Development :: Libraries
